<?xml version="1.0" encoding="UTF-8"?>
<persistence xmlns="http://xmlns.jcp.org/xml/ns/persistence" version="2.1">

    <persistence-unit name="TaskManagerUnit">
        <provider>org.eclipse.persistence.jpa.PersistenceProvider</provider>
<!--         <jta-data-source>jdbc/__MariaDB</jta-data-source> -->
        <jta-data-source>jdbc/_PostgresDB</jta-data-source>
        <properties>        .
<!--             <property name="javax.persistence.schema-generation.database.action" value="create"/> -->
<!--             <property name="javax.persistence.schema-generation.database.action" value="drop-and-create"/> -->
<!--             <property name="javax.persistence.schema-generation.create-source" value="metadata"/> -->
<!--             <property name="javax.persistence.schema-generation.scripts.action" value="drop-and-create"/> -->
<!--             <property name="javax.persistence.schema-generation.scripts.create-target" value="./create.sql"/> -->
<!--             <property name="javax.persistence.schema-generation.scripts.drop-target" value="./drop.sql"/> -->
        </properties>
    </persistence-unit>
</persistence>
